pinjet/__init__.py
pinjet/common/__init__.py
pinjet/common/constants/__init__.py
pinjet/common/constants/constants.py
pinjet/common/constants/io/__init__.py
pinjet/common/constants/io/io.py
pinjet/common/decorators/__init__.py
pinjet/common/decorators/function_timer.py
pinjet/common/decorators/retry_on_exception.py
pinjet_common-1.0.2.dist-info/LICENSE
pinjet_common-1.0.2.dist-info/METADATA
pinjet_common-1.0.2.dist-info/WHEEL
pinjet_common-1.0.2.dist-info/top_level.txt
pinjet_common-1.0.2.dist-info/RECORD
