Metadata-Version: 2.1
Name: pinjet-common
Version: 1.0.2
Summary: Common constants used throughout pinjet projects
Author: abetrack3 (Abrar Shahriar Abeed)
Author-email: <abrarshahriar2361@gmail.com>
License-File: LICENSE
Requires-Dist: StrEnum
